[
  {
    "code": "OV316",
    "date": "3JUL",
    "destination": "Giza",
    "stdEtd": "0035/0349",
    "status": "Arrived",
    "airline": "Salam Air",
    "sourceDestination": "Giza",
    "scheduledAt": "2026-07-03T00:35:00+04:00",
    "estimatedAt": "2026-07-03T03:49:00+04:00",
    "gate": "",
    "terminal": "",
    "remarks": "",
    "lastUpdated": "2026-07-03T01:14:14+00:00",
    "firstSeen": "2026-07-03T01:14:14+00:00",
    "direction": "arrival"
  },
  {
    "code": "IX441",
    "date": "3JUL",
    "destination": "Cochin",
    "stdEtd": "0150/1004",
    "status": "Cancelled",
    "airline": "Air India Express",
    "sourceDestination": "Cochin",
    "scheduledAt": "2026-07-03T01:50:00+04:00",
    "estimatedAt": "2026-07-03T10:04:00+04:00",
    "gate": "",
    "terminal": "",
    "remarks": "",
    "lastUpdated": "2026-07-03T01:14:14+00:00",
    "firstSeen": "2026-07-03T01:14:14+00:00",
    "direction": "arrival"
  },
  {
    "code": "WY103",
    "date": "3JUL",
    "destination": "LHR",
    "stdEtd": "0105",
    "status": "Departed",
    "airline": "Oman Air",
    "sourceDestination": "London",
    "scheduledAt": "2026-07-03T01:05:00+04:00",
    "estimatedAt": "",
    "gate": "",
    "terminal": "",
    "remarks": "",
    "lastUpdated": "2026-07-03T01:14:14+00:00",
    "firstSeen": "2026-07-03T01:14:14+00:00",
    "direction": "departure"
  },
  {
    "code": "OV401",
    "date": "3JUL",
    "destination": "Chittagong",
    "stdEtd": "0115/0202",
    "status": "Departed",
    "airline": "Salam Air",
    "sourceDestination": "Chittagong",
    "scheduledAt": "2026-07-03T01:15:00+04:00",
    "estimatedAt": "2026-07-03T02:02:00+04:00",
    "gate": "",
    "terminal": "",
    "remarks": "",
    "lastUpdated": "2026-07-03T01:14:14+00:00",
    "firstSeen": "2026-07-03T01:14:14+00:00",
    "direction": "departure"
  },
  {
    "code": "WY909",
    "date": "3JUL",
    "destination": "Salalah",
    "stdEtd": "0130",
    "status": "Departed",
    "airline": "Oman Air",
    "sourceDestination": "Salalah",
    "scheduledAt": "2026-07-03T01:30:00+04:00",
    "estimatedAt": "",
    "gate": "",
    "terminal": "",
    "remarks": "",
    "lastUpdated": "2026-07-03T01:14:14+00:00",
    "firstSeen": "2026-07-03T01:14:14+00:00",
    "direction": "departure"
  },
  {
    "code": "WY685",
    "date": "3JUL",
    "destination": "Riyadh",
    "stdEtd": "0145",
    "status": "Departed",
    "airline": "Oman Air",
    "sourceDestination": "Riyadh",
    "scheduledAt": "2026-07-03T01:45:00+04:00",
    "estimatedAt": "",
    "gate": "",
    "terminal": "",
    "remarks": "",
    "lastUpdated": "2026-07-03T01:14:14+00:00",
    "firstSeen": "2026-07-03T01:14:14+00:00",
    "direction": "departure"
  },
  {
    "code": "WY849",
    "date": "3JUL",
    "destination": "Jakarta",
    "stdEtd": "0150",
    "status": "Departed",
    "airline": "Oman Air",
    "sourceDestination": "Jakarta",
    "scheduledAt": "2026-07-03T01:50:00+04:00",
    "estimatedAt": "",
    "gate": "",
    "terminal": "",
    "remarks": "",
    "lastUpdated": "2026-07-03T01:14:14+00:00",
    "firstSeen": "2026-07-03T01:14:14+00:00",
    "direction": "departure"
  },
  {
    "code": "OV761",
    "date": "3JUL",
    "destination": "Mumbai",
    "stdEtd": "0125/0212",
    "status": "Departed",
    "airline": "Salam Air",
    "sourceDestination": "Mumbai",
    "scheduledAt": "2026-07-03T01:25:00+04:00",
    "estimatedAt": "2026-07-03T02:12:00+04:00",
    "gate": "",
    "terminal": "",
    "remarks": "",
    "lastUpdated": "2026-07-03T01:14:14+00:00",
    "firstSeen": "2026-07-03T01:14:14+00:00",
    "direction": "departure"
  },
  {
    "code": "TK775",
    "date": "3JUL",
    "destination": "Istanbul",
    "stdEtd": "0130/0219",
    "status": "Departed",
    "airline": "Turkish Airlines",
    "sourceDestination": "Istanbul",
    "scheduledAt": "2026-07-03T01:30:00+04:00",
    "estimatedAt": "2026-07-03T02:19:00+04:00",
    "gate": "",
    "terminal": "",
    "remarks": "",
    "lastUpdated": "2026-07-03T01:14:14+00:00",
    "firstSeen": "2026-07-03T01:14:14+00:00",
    "direction": "departure"
  },
  {
    "code": "BS322",
    "date": "3JUL",
    "destination": "Dhaka",
    "stdEtd": "0200",
    "status": "Departed",
    "airline": "BS",
    "sourceDestination": "Dhaka",
    "scheduledAt": "2026-07-03T02:00:00+04:00",
    "estimatedAt": "",
    "gate": "",
    "terminal": "",
    "remarks": "",
    "lastUpdated": "2026-07-03T01:14:14+00:00",
    "firstSeen": "2026-07-03T01:14:14+00:00",
    "direction": "departure"
  },
  {
    "code": "WY251",
    "date": "3JUL",
    "destination": "Chennai",
    "stdEtd": "0205",
    "status": "Departed",
    "airline": "Oman Air",
    "sourceDestination": "Chennai",
    "scheduledAt": "2026-07-03T02:05:00+04:00",
    "estimatedAt": "",
    "gate": "",
    "terminal": "",
    "remarks": "",
    "lastUpdated": "2026-07-03T01:14:14+00:00",
    "firstSeen": "2026-07-03T01:14:14+00:00",
    "direction": "departure"
  },
  {
    "code": "WY225",
    "date": "3JUL",
    "destination": "Cochin",
    "stdEtd": "0225",
    "status": "Departed",
    "airline": "Oman Air",
    "sourceDestination": "Cochin",
    "scheduledAt": "2026-07-03T02:25:00+04:00",
    "estimatedAt": "",
    "gate": "",
    "terminal": "",
    "remarks": "",
    "lastUpdated": "2026-07-03T01:14:14+00:00",
    "firstSeen": "2026-07-03T01:14:14+00:00",
    "direction": "departure"
  },
  {
    "code": "WY211",
    "date": "3JUL",
    "destination": "Thiruvananthapuram",
    "stdEtd": "0225",
    "status": "Departed",
    "airline": "Oman Air",
    "sourceDestination": "Thiruvananthapuram",
    "scheduledAt": "2026-07-03T02:25:00+04:00",
    "estimatedAt": "",
    "gate": "",
    "terminal": "",
    "remarks": "",
    "lastUpdated": "2026-07-03T01:14:14+00:00",
    "firstSeen": "2026-07-03T01:14:14+00:00",
    "direction": "departure"
  },
  {
    "code": "WY235",
    "date": "3JUL",
    "destination": "Hyderabad",
    "stdEtd": "0245",
    "status": "Departed",
    "airline": "Oman Air",
    "sourceDestination": "Hyderabad",
    "scheduledAt": "2026-07-03T02:45:00+04:00",
    "estimatedAt": "",
    "gate": "",
    "terminal": "",
    "remarks": "",
    "lastUpdated": "2026-07-03T01:14:14+00:00",
    "firstSeen": "2026-07-03T01:14:14+00:00",
    "direction": "departure"
  },
  {
    "code": "IX892",
    "date": "3JUL",
    "destination": "Mangalore",
    "stdEtd": "0255",
    "status": "Departed",
    "airline": "Air India Express",
    "sourceDestination": "Mangalore",
    "scheduledAt": "2026-07-03T02:55:00+04:00",
    "estimatedAt": "",
    "gate": "",
    "terminal": "",
    "remarks": "",
    "lastUpdated": "2026-07-03T01:14:14+00:00",
    "firstSeen": "2026-07-03T01:14:14+00:00",
    "direction": "departure"
  },
  {
    "code": "OV463",
    "date": "3JUL",
    "destination": "Bangkok",
    "stdEtd": "0025/0322",
    "status": "Departed",
    "airline": "Salam Air",
    "sourceDestination": "Bangkok",
    "scheduledAt": "2026-07-03T00:25:00+04:00",
    "estimatedAt": "2026-07-03T03:22:00+04:00",
    "gate": "",
    "terminal": "",
    "remarks": "",
    "lastUpdated": "2026-07-03T01:14:14+00:00",
    "firstSeen": "2026-07-03T01:14:14+00:00",
    "direction": "departure"
  },
  {
    "code": "WY671",
    "date": "3JUL",
    "destination": "JED",
    "stdEtd": "0225",
    "status": "Departed",
    "airline": "Oman Air",
    "sourceDestination": "Jeddah",
    "scheduledAt": "2026-07-03T02:25:00+04:00",
    "estimatedAt": "",
    "gate": "",
    "terminal": "",
    "remarks": "",
    "lastUpdated": "2026-07-03T01:14:14+00:00",
    "firstSeen": "2026-07-03T01:14:14+00:00",
    "direction": "departure"
  },
  {
    "code": "6E1274",
    "date": "3JUL",
    "destination": "Hyderabad",
    "stdEtd": "0250/0337",
    "status": "Departed",
    "airline": "6E",
    "sourceDestination": "Hyderabad",
    "scheduledAt": "2026-07-03T02:50:00+04:00",
    "estimatedAt": "2026-07-03T03:37:00+04:00",
    "gate": "",
    "terminal": "",
    "remarks": "",
    "lastUpdated": "2026-07-03T01:14:14+00:00",
    "firstSeen": "2026-07-03T01:14:14+00:00",
    "direction": "departure"
  },
  {
    "code": "WY265",
    "date": "3JUL",
    "destination": "Lucknow",
    "stdEtd": "0300",
    "status": "Departed",
    "airline": "Oman Air",
    "sourceDestination": "Lucknow",
    "scheduledAt": "2026-07-03T03:00:00+04:00",
    "estimatedAt": "",
    "gate": "",
    "terminal": "",
    "remarks": "",
    "lastUpdated": "2026-07-03T01:14:14+00:00",
    "firstSeen": "2026-07-03T01:14:14+00:00",
    "direction": "departure"
  },
  {
    "code": "6E1272",
    "date": "3JUL",
    "destination": "Cochin",
    "stdEtd": "0300",
    "status": "Departed",
    "airline": "6E",
    "sourceDestination": "Cochin",
    "scheduledAt": "2026-07-03T03:00:00+04:00",
    "estimatedAt": "",
    "gate": "",
    "terminal": "",
    "remarks": "",
    "lastUpdated": "2026-07-03T01:14:14+00:00",
    "firstSeen": "2026-07-03T01:14:14+00:00",
    "direction": "departure"
  },
  {
    "code": "6Q782",
    "date": "3JUL",
    "destination": "Damascus",
    "stdEtd": "0300/0342",
    "status": "Departed",
    "airline": "6Q",
    "sourceDestination": "Damascus",
    "scheduledAt": "2026-07-03T03:00:00+04:00",
    "estimatedAt": "2026-07-03T03:42:00+04:00",
    "gate": "",
    "terminal": "",
    "remarks": "",
    "lastUpdated": "2026-07-03T01:14:14+00:00",
    "firstSeen": "2026-07-03T01:14:14+00:00",
    "direction": "departure"
  },
  {
    "code": "WY297",
    "date": "3JUL",
    "destination": "Calicut",
    "stdEtd": "0305",
    "status": "Departed",
    "airline": "Oman Air",
    "sourceDestination": "Calicut",
    "scheduledAt": "2026-07-03T03:05:00+04:00",
    "estimatedAt": "",
    "gate": "",
    "terminal": "",
    "remarks": "",
    "lastUpdated": "2026-07-03T01:14:14+00:00",
    "firstSeen": "2026-07-03T01:14:14+00:00",
    "direction": "departure"
  },
  {
    "code": "WY241",
    "date": "3JUL",
    "destination": "Delhi",
    "stdEtd": "0320",
    "status": "Departed",
    "airline": "Oman Air",
    "sourceDestination": "Delhi",
    "scheduledAt": "2026-07-03T03:20:00+04:00",
    "estimatedAt": "",
    "gate": "",
    "terminal": "",
    "remarks": "",
    "lastUpdated": "2026-07-03T01:14:14+00:00",
    "firstSeen": "2026-07-03T01:14:14+00:00",
    "direction": "departure"
  },
  {
    "code": "OV597",
    "date": "3JUL",
    "destination": "Peshawar",
    "stdEtd": "0120/0432",
    "status": "Scheduled",
    "airline": "Salam Air",
    "sourceDestination": "Peshawar",
    "scheduledAt": "2026-07-03T01:20:00+04:00",
    "estimatedAt": "2026-07-03T04:32:00+04:00",
    "gate": "",
    "terminal": "",
    "remarks": "",
    "lastUpdated": "2026-07-03T01:14:14+00:00",
    "firstSeen": "2026-07-03T01:14:14+00:00",
    "direction": "departure"
  },
  {
    "code": "PK292",
    "date": "3JUL",
    "destination": "Islamabad",
    "stdEtd": "0245/0408",
    "status": "Departed",
    "airline": "PIA Pakistan International Airlines",
    "sourceDestination": "Islamabad",
    "scheduledAt": "2026-07-03T02:45:00+04:00",
    "estimatedAt": "2026-07-03T04:08:00+04:00",
    "gate": "",
    "terminal": "",
    "remarks": "",
    "lastUpdated": "2026-07-03T01:14:14+00:00",
    "firstSeen": "2026-07-03T01:14:14+00:00",
    "direction": "departure"
  },
  {
    "code": "IX442",
    "date": "3JUL",
    "destination": "Cochin",
    "stdEtd": "0250/1100",
    "status": "Cancelled",
    "airline": "Air India Express",
    "sourceDestination": "Cochin",
    "scheduledAt": "2026-07-03T02:50:00+04:00",
    "estimatedAt": "2026-07-03T11:00:00+04:00",
    "gate": "",
    "terminal": "",
    "remarks": "",
    "lastUpdated": "2026-07-03T01:14:14+00:00",
    "firstSeen": "2026-07-03T01:14:14+00:00",
    "direction": "departure"
  },
  {
    "code": "IX236",
    "date": "3JUL",
    "destination": "Mumbai",
    "stdEtd": "0015/0052",
    "status": "Departed",
    "airline": "Air India Express",
    "sourceDestination": "Mumbai",
    "scheduledAt": "2026-07-03T00:15:00+04:00",
    "estimatedAt": "2026-07-03T00:52:00+04:00",
    "gate": "",
    "terminal": "",
    "remarks": "",
    "lastUpdated": "2026-07-03T01:14:14+00:00",
    "firstSeen": "2026-07-03T01:14:14+00:00",
    "direction": "departure"
  },
  {
    "code": "OV795",
    "date": "3JUL",
    "destination": "Jaipur",
    "stdEtd": "0035/0100",
    "status": "Departed",
    "airline": "Salam Air",
    "sourceDestination": "Jaipur",
    "scheduledAt": "2026-07-03T00:35:00+04:00",
    "estimatedAt": "2026-07-03T01:00:00+04:00",
    "gate": "",
    "terminal": "",
    "remarks": "",
    "lastUpdated": "2026-07-03T01:14:14+00:00",
    "firstSeen": "2026-07-03T01:14:14+00:00",
    "direction": "departure"
  }
]
