{
  "status": "success",
  "message": "تم التحديث بنجاح",
  "liveFlightsCount": 202,
  "archiveFlightsCount": 3598,
  "liveArrivalsCount": 81,
  "liveDeparturesCount": 121,
  "archiveArrivalsCount": 1747,
  "archiveDeparturesCount": 1851,
  "sourceUrl": "https://www.muscatairport.co.om/flightstatusframe?type=2",
  "arrivalUrl": "https://www.muscatairport.co.om/flightstatusframe?type=1",
  "departureUrl": "https://www.muscatairport.co.om/flightstatusframe?type=2",
  "updatedAt": "2026-07-09T05:17:55+00:00",
  "timezone": "Asia/Muscat"
}
